peerberrypy/__init__.py
peerberrypy/api.py
peerberrypy/constants.py
peerberrypy/endpoints.py
peerberrypy/exceptions.py
peerberrypy/request_handler.py
peerberrypy/utils.py
peerberrypy-1.9.0.dist-info/LICENSE.md
peerberrypy-1.9.0.dist-info/METADATA
peerberrypy-1.9.0.dist-info/WHEEL
peerberrypy-1.9.0.dist-info/top_level.txt
peerberrypy-1.9.0.dist-info/RECORD
