Metadata-Version: 2.1
Name: peerberrypy
Version: 1.9.0
Summary: Python API Wrapper for PeerBerry
Author-email: Tomás Perestrelo <tomasperestrelo21@gmail.com>
License: MIT License
Project-URL: Repository, https://github.com/thicccat688/peerberrypy
Keywords: python,api,api-wrapper,peerberrypy
Requires-Python: >=3.8
License-File: LICENSE.md
Requires-Dist: cloudscraper >=1.2
Provides-Extra: otp
Requires-Dist: pyotp <3,>=2.7.0 ; extra == 'otp'
Provides-Extra: pandas
Requires-Dist: pandas <2 ; extra == 'pandas'
Requires-Dist: openpyxl <4,>=3.0 ; extra == 'pandas'
